mycalcpkg/__init__.py
mycalcpkg-1.dist-info/METADATA
mycalcpkg-1.dist-info/WHEEL
mycalcpkg-1.dist-info/top_level.txt
mycalcpkg-1.dist-info/RECORD
