Metadata-Version: 2.1
Name: mycalcpkg
Version: 1
Summary: A Super Fun Package For Adding & Subtracting.
Author: <name>
